uzombie/__init__.py
uzombie/__main__.py
uzombie/cli.py
uzombie/callbacks/__init__.py
uzombie/callbacks/auto_dora.py
uzombie/callbacks/exact_time_stop.py
uzombie/callbacks/peso_restart.py
uzombie/callbacks/research.py
uzombie/core/hardware.py
uzombie/core/hybrid_projector.py
uzombie/core/optimizer.py
uzombie/trainer/uzombie_trainer.py
uzombie/utils/benchmarks.py
uzombie/utils/logger.py
uzombie/utils/upload.py
uzombie-1.0.2.dist-info/METADATA
uzombie-1.0.2.dist-info/WHEEL
uzombie-1.0.2.dist-info/entry_points.txt
uzombie-1.0.2.dist-info/top_level.txt
uzombie-1.0.2.dist-info/RECORD
