Metadata-Version: 2.4
Name: uzombie
Version: 1.0.2
Summary: The fastest LLM fine-tuning engine on Earth
Author-email: Kafoo <kafoo@protonmail.com>
License-Expression: MIT
Project-URL: Homepage, https://github.com/kafoo/uzombie
Project-URL: Bug Tracker, https://github.com/kafoo/uzombie/issues
Project-URL: Discussions, https://github.com/kafoo/uzombie/discussions
Project-URL: Leaderboard, https://huggingface.co/spaces/kafoo/uzombie-leaderboard
Keywords: llm,fine-tuning,lora,qlora,unsloth,fast,galore,dora
Classifier: Programming Language :: Python :: 3
Classifier: Operating System :: OS Independent
Classifier: Topic :: Scientific/Engineering :: Artificial Intelligence
Classifier: Intended Audience :: Developers
Classifier: Intended Audience :: Science/Research
Requires-Python: >=3.10
Requires-Dist: torch>=2.4.0
Requires-Dist: unsloth==2025.12.8
Requires-Dist: unsloth_zoo==2025.12.6
Requires-Dist: transformers>=4.57.0
Requires-Dist: trl>=0.24.0
Requires-Dist: peft>=0.18.0
Requires-Dist: datasets>=4.3.0
Requires-Dist: accelerate>=1.12.0
Requires-Dist: bitsandbytes>=0.49.0
Requires-Dist: rich>=13.0
Requires-Dist: huggingface-hub>=0.36.0
Requires-Dist: tqdm
Requires-Dist: tyro
Requires-Dist: tensorly>=0.9.0
Requires-Dist: scikit-learn>=1.8.0
Requires-Dist: psutil
Provides-Extra: dev
Requires-Dist: pytest; extra == "dev"
Requires-Dist: lm-eval>=0.4.9; extra == "dev"
